peregrine/__init__.py
peregrine/cli.py
peregrine/client.py
peregrine/colorutils.py
peregrine/errors.py
peregrine/install.py
peregrine/main.py
peregrine/stateutils.py
PlatitudeTerminal-1.0.8.dist-info/METADATA
PlatitudeTerminal-1.0.8.dist-info/WHEEL
PlatitudeTerminal-1.0.8.dist-info/entry_points.txt
PlatitudeTerminal-1.0.8.dist-info/top_level.txt
PlatitudeTerminal-1.0.8.dist-info/RECORD
