Metadata-Version: 2.1
Name: PlatitudeTerminal
Version: 1.0.8
Summary: "Natural language command line queries."
Author: Louis Smidt
Requires-Python: >3.8
Requires-Dist: halo
Requires-Dist: typer (>=0.7.0)
Requires-Dist: python-dotenv (>=1.0.0)
Requires-Dist: Pyrebase4 (>=4.6.0)
Requires-Dist: pyjwt (>=2.0.1)
Requires-Dist: keyring (>=23.13.1)
Requires-Dist: prompt-toolkit
Requires-Dist: packaging
Requires-Dist: requests (==2.28.0)
Requires-Dist: requests-toolbelt (==0.10.1)
